htmljet/__init__.py
htmljet/__main__.py
htmljet/main.py
htmljet/tests/test_main.py
htmljet-0.1.1.dist-info/METADATA
htmljet-0.1.1.dist-info/WHEEL
htmljet-0.1.1.dist-info/entry_points.txt
htmljet-0.1.1.dist-info/RECORD
