Metadata-Version: 2.3
Name: htmljet
Version: 0.1.1
Summary: A CLI tool to take screenshots of HTML pages
Requires-Python: >=3.12
Requires-Dist: beautifulsoup4>=4.12.3
Requires-Dist: playwright>=1.47.0
Requires-Dist: rich>=13.8.1
Requires-Dist: typer>=0.12.5
